{
  "session_metadata": {
    "patient_id": "Colton",
    "date": "2025-11-10",
    "clinician": "",
    "notes": "",
    "trial_name": "Postop",
    "trial_order": 5
  },
  "trial_summaries": {
    "hsv": {
      "sample_count": 592,
      "duration_sec": 19.98499999998603,
      "fps_avg": 29.62221666251758,
      "err_px": {
        "mean": 26.961002518257686,
        "median": 25.951128510868198,
        "std": 14.50963720557152,
        "p90": 46.494527833700836,
        "p95": 55.30595135956946,
        "max": 69.89155281831427
      },
      "rmse_time_weighted": 30.554231252574812,
      "tracking_loss_rate": 0.0,
      "mean_depth_mm": 387.2073608617594,
      "valid_depth_fraction_avg": 0.9408783783783784
    }
  },
  "signal_analysis": {
    "hsv": {
      "rms_px": 16.496351334154344,
      "rms_tremor_band_px": 1.029938827116633,
      "tremor_band_power": 1.3119227120931345,
      "tremor_band_hz": [
        4.0,
        10.0
      ],
      "resampled_len": 599,
      "sampling_rate_hz": 30.0,
      "psd_temporal": [
        {
          "freq_hz": 0.0,
          "psd": 29.91841339365445
        },
        {
          "freq_hz": 0.20134228187919462,
          "psd": 166.16408541560958
        },
        {
          "freq_hz": 0.40268456375838924,
          "psd": 95.83569802447765
        },
        {
          "freq_hz": 0.6040268456375839,
          "psd": 49.79416897236748
        },
        {
          "freq_hz": 0.8053691275167785,
          "psd": 39.56760438981007
        },
        {
          "freq_hz": 1.006711409395973,
          "psd": 27.87777967290296
        },
        {
          "freq_hz": 1.2080536912751678,
          "psd": 32.101197566351956
        },
        {
          "freq_hz": 1.4093959731543624,
          "psd": 8.568655974024749
        },
        {
          "freq_hz": 1.610738255033557,
          "psd": 3.6092574508664548
        },
        {
          "freq_hz": 1.8120805369127515,
          "psd": 2.302381873700741
        },
        {
          "freq_hz": 2.013422818791946,
          "psd": 1.9021445544628868
        },
        {
          "freq_hz": 2.2147651006711406,
          "psd": 2.263407257113193
        },
        {
          "freq_hz": 2.4161073825503356,
          "psd": 1.9563171011282479
        },
        {
          "freq_hz": 2.61744966442953,
          "psd": 0.7477340648487595
        },
        {
          "freq_hz": 2.8187919463087248,
          "psd": 0.7519447326223191
        },
        {
          "freq_hz": 3.0201342281879193,
          "psd": 0.45320694450617915
        },
        {
          "freq_hz": 3.221476510067114,
          "psd": 0.5234415349598148
        },
        {
          "freq_hz": 3.4228187919463084,
          "psd": 0.480819040603844
        },
        {
          "freq_hz": 3.624161073825503,
          "psd": 0.37348136011641875
        },
        {
          "freq_hz": 3.8255033557046976,
          "psd": 0.41790068040261097
        },
        {
          "freq_hz": 4.026845637583892,
          "psd": 0.24238778004226322
        },
        {
          "freq_hz": 4.228187919463087,
          "psd": 0.22174883537530718
        },
        {
          "freq_hz": 4.429530201342281,
          "psd": 0.12103205586026745
        },
        {
          "freq_hz": 4.630872483221476,
          "psd": 0.14094788607210887
        },
        {
          "freq_hz": 4.832214765100671,
          "psd": 0.20357571135174543
        },
        {
          "freq_hz": 5.033557046979865,
          "psd": 0.24105975324824763
        },
        {
          "freq_hz": 5.23489932885906,
          "psd": 0.17767184525084614
        },
        {
          "freq_hz": 5.4362416107382545,
          "psd": 0.48543781889874366
        },
        {
          "freq_hz": 5.6375838926174495,
          "psd": 0.4751073757730348
        },
        {
          "freq_hz": 5.838926174496644,
          "psd": 0.37639648349795235
        },
        {
          "freq_hz": 6.040268456375839,
          "psd": 0.22326104501622174
        },
        {
          "freq_hz": 6.241610738255033,
          "psd": 0.19051291067573542
        },
        {
          "freq_hz": 6.442953020134228,
          "psd": 0.24916019399571512
        },
        {
          "freq_hz": 6.644295302013423,
          "psd": 0.30543518452848156
        },
        {
          "freq_hz": 6.845637583892617,
          "psd": 0.44383551661559684
        },
        {
          "freq_hz": 7.046979865771812,
          "psd": 0.40882275967274545
        },
        {
          "freq_hz": 7.248322147651006,
          "psd": 0.3125170637186901
        },
        {
          "freq_hz": 7.449664429530201,
          "psd": 0.2419553441654089
        },
        {
          "freq_hz": 7.651006711409395,
          "psd": 0.17071886446095555
        },
        {
          "freq_hz": 7.85234899328859,
          "psd": 0.08375172088978318
        },
        {
          "freq_hz": 8.053691275167784,
          "psd": 0.09066132737703425
        },
        {
          "freq_hz": 8.25503355704698,
          "psd": 0.12374866504016353
        },
        {
          "freq_hz": 8.456375838926174,
          "psd": 0.14565078052177036
        },
        {
          "freq_hz": 8.657718120805368,
          "psd": 0.05927377719357006
        },
        {
          "freq_hz": 8.859060402684563,
          "psd": 0.1292540350188876
        },
        {
          "freq_hz": 9.060402684563758,
          "psd": 0.232591121973625
        },
        {
          "freq_hz": 9.261744966442953,
          "psd": 0.2130876371548696
        },
        {
          "freq_hz": 9.463087248322147,
          "psd": 0.137532831500741
        },
        {
          "freq_hz": 9.664429530201343,
          "psd": 0.12634118308087797
        },
        {
          "freq_hz": 9.865771812080537,
          "psd": 0.12719837089128425
        },
        {
          "freq_hz": 10.06711409395973,
          "psd": 0.148789356770003
        },
        {
          "freq_hz": 10.268456375838925,
          "psd": 0.21898158279601862
        },
        {
          "freq_hz": 10.46979865771812,
          "psd": 0.20862239980893524
        },
        {
          "freq_hz": 10.671140939597315,
          "psd": 0.15889154570455746
        },
        {
          "freq_hz": 10.872483221476509,
          "psd": 0.21084838971004297
        },
        {
          "freq_hz": 11.073825503355703,
          "psd": 0.19775106319735497
        },
        {
          "freq_hz": 11.275167785234899,
          "psd": 0.11974984306728877
        },
        {
          "freq_hz": 11.476510067114093,
          "psd": 0.09458575576011866
        },
        {
          "freq_hz": 11.677852348993287,
          "psd": 0.15417659164884917
        },
        {
          "freq_hz": 11.879194630872483,
          "psd": 0.14370503581116426
        },
        {
          "freq_hz": 12.080536912751677,
          "psd": 0.12028207094946348
        },
        {
          "freq_hz": 12.281879194630871,
          "psd": 0.05124309755889972
        },
        {
          "freq_hz": 12.483221476510066,
          "psd": 0.03608996648292595
        },
        {
          "freq_hz": 12.684563758389261,
          "psd": 0.07630282389924006
        },
        {
          "freq_hz": 12.885906040268456,
          "psd": 0.10370291191233309
        },
        {
          "freq_hz": 13.08724832214765,
          "psd": 0.08450432343803511
        },
        {
          "freq_hz": 13.288590604026846,
          "psd": 0.037237499113795106
        },
        {
          "freq_hz": 13.48993288590604,
          "psd": 0.04405011611344727
        },
        {
          "freq_hz": 13.691275167785234,
          "psd": 0.06189125936958294
        },
        {
          "freq_hz": 13.892617449664428,
          "psd": 0.053816092902461775
        },
        {
          "freq_hz": 14.093959731543624,
          "psd": 0.025218105886071724
        },
        {
          "freq_hz": 14.295302013422818,
          "psd": 0.03429324498476274
        },
        {
          "freq_hz": 14.496644295302012,
          "psd": 0.05830011683276989
        },
        {
          "freq_hz": 14.697986577181208,
          "psd": 0.05380631701955429
        },
        {
          "freq_hz": 14.899328859060402,
          "psd": 0.0763943729500099
        }
      ],
      "psd_tremor_filtered": [
        {
          "freq_hz": 0.0,
          "psd": 0.0005374838800438989
        },
        {
          "freq_hz": 0.20134228187919462,
          "psd": 0.0002680665173064429
        },
        {
          "freq_hz": 0.40268456375838924,
          "psd": 1.433846933569211e-09
        },
        {
          "freq_hz": 0.6040268456375839,
          "psd": 1.7375165419169504e-09
        },
        {
          "freq_hz": 0.8053691275167785,
          "psd": 2.435634438794334e-09
        },
        {
          "freq_hz": 1.006711409395973,
          "psd": 2.9480892764448824e-09
        },
        {
          "freq_hz": 1.2080536912751678,
          "psd": 4.209920858468842e-09
        },
        {
          "freq_hz": 1.4093959731543624,
          "psd": 1.0491642218759489e-08
        },
        {
          "freq_hz": 1.610738255033557,
          "psd": 3.217466203244934e-08
        },
        {
          "freq_hz": 1.8120805369127515,
          "psd": 8.411743340059615e-08
        },
        {
          "freq_hz": 2.013422818791946,
          "psd": 5.99749534447389e-07
        },
        {
          "freq_hz": 2.2147651006711406,
          "psd": 4.531357110260381e-06
        },
        {
          "freq_hz": 2.4161073825503356,
          "psd": 1.0554372525252796e-05
        },
        {
          "freq_hz": 2.61744966442953,
          "psd": 3.158739268816322e-05
        },
        {
          "freq_hz": 2.8187919463087248,
          "psd": 0.00015376073969311708
        },
        {
          "freq_hz": 3.0201342281879193,
          "psd": 0.0004110614453494742
        },
        {
          "freq_hz": 3.221476510067114,
          "psd": 0.002138795611572688
        },
        {
          "freq_hz": 3.4228187919463084,
          "psd": 0.005002443078111154
        },
        {
          "freq_hz": 3.624161073825503,
          "psd": 0.018494971107536055
        },
        {
          "freq_hz": 3.8255033557046976,
          "psd": 0.05339228790803204
        },
        {
          "freq_hz": 4.026845637583892,
          "psd": 0.06524224404308165
        },
        {
          "freq_hz": 4.228187919463087,
          "psd": 0.11054734980706181
        },
        {
          "freq_hz": 4.429530201342281,
          "psd": 0.07810498177803256
        },
        {
          "freq_hz": 4.630872483221476,
          "psd": 0.12037135147250178
        },
        {
          "freq_hz": 4.832214765100671,
          "psd": 0.19114673497898707
        },
        {
          "freq_hz": 5.033557046979865,
          "psd": 0.23400311091990858
        },
        {
          "freq_hz": 5.23489932885906,
          "psd": 0.17621229630025562
        },
        {
          "freq_hz": 5.4362416107382545,
          "psd": 0.48400253358212536
        },
        {
          "freq_hz": 5.6375838926174495,
          "psd": 0.47460809695611506
        },
        {
          "freq_hz": 5.838926174496644,
          "psd": 0.3762120182904279
        },
        {
          "freq_hz": 6.040268456375839,
          "psd": 0.22330832726227204
        },
        {
          "freq_hz": 6.241610738255033,
          "psd": 0.19046653057222546
        },
        {
          "freq_hz": 6.442953020134228,
          "psd": 0.24918382518352994
        },
        {
          "freq_hz": 6.644295302013423,
          "psd": 0.3054590529825494
        },
        {
          "freq_hz": 6.845637583892617,
          "psd": 0.4438056027174184
        },
        {
          "freq_hz": 7.046979865771812,
          "psd": 0.4088229932706938
        },
        {
          "freq_hz": 7.248322147651006,
          "psd": 0.31251704705047356
        },
        {
          "freq_hz": 7.449664429530201,
          "psd": 0.2419735001695658
        },
        {
          "freq_hz": 7.651006711409395,
          "psd": 0.17069402933822503
        },
        {
          "freq_hz": 7.85234899328859,
          "psd": 0.08374741381579491
        },
        {
          "freq_hz": 8.053691275167784,
          "psd": 0.09061090209664362
        },
        {
          "freq_hz": 8.25503355704698,
          "psd": 0.12353656318034009
        },
        {
          "freq_hz": 8.456375838926174,
          "psd": 0.1450447548681617
        },
        {
          "freq_hz": 8.657718120805368,
          "psd": 0.058629846974382546
        },
        {
          "freq_hz": 8.859060402684563,
          "psd": 0.12381778413701985
        },
        {
          "freq_hz": 9.060402684563758,
          "psd": 0.2159505433163893
        },
        {
          "freq_hz": 9.261744966442953,
          "psd": 0.18528506581476747
        },
        {
          "freq_hz": 9.463087248322147,
          "psd": 0.10182310285787842
        },
        {
          "freq_hz": 9.664429530201343,
          "psd": 0.07115240453098473
        },
        {
          "freq_hz": 9.865771812080537,
          "psd": 0.04551020310155924
        },
        {
          "freq_hz": 10.06711409395973,
          "psd": 0.029373521728642903
        },
        {
          "freq_hz": 10.268456375838925,
          "psd": 0.018464780456649198
        },
        {
          "freq_hz": 10.46979865771812,
          "psd": 0.008878121182392534
        },
        {
          "freq_hz": 10.671140939597315,
          "psd": 0.002137687729184876
        },
        {
          "freq_hz": 10.872483221476509,
          "psd": 0.0008885356168533622
        },
        {
          "freq_hz": 11.073825503355703,
          "psd": 0.00028782106199678765
        },
        {
          "freq_hz": 11.275167785234899,
          "psd": 6.222657926928077e-05
        },
        {
          "freq_hz": 11.476510067114093,
          "psd": 1.0388957439422691e-05
        },
        {
          "freq_hz": 11.677852348993287,
          "psd": 5.179120500643257e-06
        },
        {
          "freq_hz": 11.879194630872483,
          "psd": 1.4174703611551541e-06
        },
        {
          "freq_hz": 12.080536912751677,
          "psd": 4.391035416579725e-07
        },
        {
          "freq_hz": 12.281879194630871,
          "psd": 5.302473858324525e-08
        },
        {
          "freq_hz": 12.483221476510066,
          "psd": 7.971672433151963e-09
        },
        {
          "freq_hz": 12.684563758389261,
          "psd": 7.34828425846744e-09
        },
        {
          "freq_hz": 12.885906040268456,
          "psd": 4.036277629095166e-09
        },
        {
          "freq_hz": 13.08724832214765,
          "psd": 2.7493511459382406e-09
        },
        {
          "freq_hz": 13.288590604026846,
          "psd": 1.7130342576168645e-09
        },
        {
          "freq_hz": 13.48993288590604,
          "psd": 1.3525907291122699e-09
        },
        {
          "freq_hz": 13.691275167785234,
          "psd": 1.0346474403791892e-09
        },
        {
          "freq_hz": 13.892617449664428,
          "psd": 8.314851204023228e-10
        },
        {
          "freq_hz": 14.093959731543624,
          "psd": 6.761955151568826e-10
        },
        {
          "freq_hz": 14.295302013422818,
          "psd": 5.697597783627032e-10
        },
        {
          "freq_hz": 14.496644295302012,
          "psd": 4.968901427364786e-10
        },
        {
          "freq_hz": 14.697986577181208,
          "psd": 4.514988009045678e-10
        },
        {
          "freq_hz": 14.899328859060402,
          "psd": 4.2971770036571685e-10
        }
      ]
    }
  },
  "directional_analysis": {
    "hsv": {
      "bin_edges": [
        0.0,
        10.0,
        20.0,
        30.0,
        40.0,
        50.0,
        60.0,
        70.0,
        80.0,
        90.0,
        100.0,
        110.0,
        120.0,
        130.0,
        140.0,
        150.0,
        160.0,
        170.0,
        180.0,
        190.0,
        200.0,
        210.0,
        220.0,
        230.0,
        240.0,
        250.0,
        260.0,
        270.0,
        280.0,
        290.0,
        300.0,
        310.0,
        320.0,
        330.0,
        340.0,
        350.0,
        360.0
      ],
      "bin_centers": [
        5.0,
        15.0,
        25.0,
        35.0,
        45.0,
        55.0,
        65.0,
        75.0,
        85.0,
        95.0,
        105.0,
        115.0,
        125.0,
        135.0,
        145.0,
        155.0,
        165.0,
        175.0,
        185.0,
        195.0,
        205.0,
        215.0,
        225.0,
        235.0,
        245.0,
        255.0,
        265.0,
        275.0,
        285.0,
        295.0,
        305.0,
        315.0,
        325.0,
        335.0,
        345.0,
        355.0
      ],
      "power_per_bin": [
        801.534654112441,
        807.3794932391869,
        927.3604882825896,
        1905.8374548350016,
        1443.0305006788483,
        1311.5496699880139,
        2072.474000408634,
        1541.4535809892539,
        1667.1945224929063,
        1697.4273435018988,
        1890.0254409340544,
        1004.9295228897533,
        1231.6782407470214,
        874.4139246932859,
        789.6396355811132,
        941.5375358951646,
        975.4680482004471,
        972.7728479490745,
        826.2641197877651,
        1185.772478164828,
        1361.6737553350586,
        1548.48318913365,
        1244.432903766438,
        1154.8125990222547,
        2595.9161775833963,
        2070.0094410109823,
        1096.6070818410506,
        1459.2308464409127,
        2325.483308351812,
        1219.35800492448,
        1137.053650522051,
        770.5479233582448,
        777.7187186204213,
        891.0655531130751,
        868.6515269864999,
        1082.131237263124
      ],
      "worst_angle": 245.0,
      "best_angle": 315.0,
      "anisotropy_ratio": 3.368922423759697,
      "mean_power": 1290.8588727956871,
      "worst_power": 2595.9161775833963,
      "best_power": 770.5479233582448,
      "tremor_band_hz": [
        4.0,
        10.0
      ],
      "sampling_rate_hz": 30.0,
      "n_samples": 600,
      "duration_sec": 19.966666662017815,
      "acceleration_tremor_rms": 1386.9394031331465
    }
  },
  "improvements": {},
  "stereo_3d": {
    "target_depth_m": 0.5,
    "disparity_px": -315.0360978299588
  }
}