{
  "session_metadata": {
    "patient_id": "Colton",
    "date": "2025-11-10",
    "clinician": "",
    "notes": "",
    "trial_name": "Intraop 2",
    "trial_order": 3
  },
  "trial_summaries": {
    "hsv": {
      "sample_count": 596,
      "duration_sec": 19.98399999999674,
      "fps_avg": 29.82385908727468,
      "err_px": {
        "mean": 40.62467134184924,
        "median": 37.27470695951611,
        "std": 22.98982553294739,
        "p90": 74.24183152348719,
        "p95": 84.50396664335571,
        "max": 118.56867459690758
      },
      "rmse_time_weighted": 46.701749073377606,
      "tracking_loss_rate": 0.0,
      "mean_depth_mm": 419.1721739130435,
      "valid_depth_fraction_avg": 0.964765100671141
    }
  },
  "signal_analysis": {
    "hsv": {
      "rms_px": 31.053020095516683,
      "rms_tremor_band_px": 8.791556917397752,
      "tremor_band_power": 91.20348549270237,
      "tremor_band_hz": [
        4.0,
        10.0
      ],
      "resampled_len": 599,
      "sampling_rate_hz": 30.0,
      "psd_temporal": [
        {
          "freq_hz": 0.0,
          "psd": 76.40226859864732
        },
        {
          "freq_hz": 0.20134228187919462,
          "psd": 197.50502971214934
        },
        {
          "freq_hz": 0.40268456375838924,
          "psd": 60.27721932750056
        },
        {
          "freq_hz": 0.6040268456375839,
          "psd": 39.624105392980745
        },
        {
          "freq_hz": 0.8053691275167785,
          "psd": 98.02420091709429
        },
        {
          "freq_hz": 1.006711409395973,
          "psd": 63.21196293690789
        },
        {
          "freq_hz": 1.2080536912751678,
          "psd": 18.36652001204599
        },
        {
          "freq_hz": 1.4093959731543624,
          "psd": 9.452913051127853
        },
        {
          "freq_hz": 1.610738255033557,
          "psd": 9.138671208395024
        },
        {
          "freq_hz": 1.8120805369127515,
          "psd": 10.739576294613343
        },
        {
          "freq_hz": 2.013422818791946,
          "psd": 19.48602520599135
        },
        {
          "freq_hz": 2.2147651006711406,
          "psd": 21.60054152810633
        },
        {
          "freq_hz": 2.4161073825503356,
          "psd": 16.384846283505233
        },
        {
          "freq_hz": 2.61744966442953,
          "psd": 27.08426235504735
        },
        {
          "freq_hz": 2.8187919463087248,
          "psd": 30.67867018401863
        },
        {
          "freq_hz": 3.0201342281879193,
          "psd": 33.23282351784085
        },
        {
          "freq_hz": 3.221476510067114,
          "psd": 63.33071872525904
        },
        {
          "freq_hz": 3.4228187919463084,
          "psd": 82.90705317340391
        },
        {
          "freq_hz": 3.624161073825503,
          "psd": 104.743165406492
        },
        {
          "freq_hz": 3.8255033557046976,
          "psd": 161.08430833469342
        },
        {
          "freq_hz": 4.026845637583892,
          "psd": 73.01995187739755
        },
        {
          "freq_hz": 4.228187919463087,
          "psd": 40.669597675286184
        },
        {
          "freq_hz": 4.429530201342281,
          "psd": 63.3307809566477
        },
        {
          "freq_hz": 4.630872483221476,
          "psd": 37.98868456645919
        },
        {
          "freq_hz": 4.832214765100671,
          "psd": 11.993354117554619
        },
        {
          "freq_hz": 5.033557046979865,
          "psd": 16.03095311381971
        },
        {
          "freq_hz": 5.23489932885906,
          "psd": 19.54965701545879
        },
        {
          "freq_hz": 5.4362416107382545,
          "psd": 17.535592896307552
        },
        {
          "freq_hz": 5.6375838926174495,
          "psd": 12.083597791496297
        },
        {
          "freq_hz": 5.838926174496644,
          "psd": 6.664355315195386
        },
        {
          "freq_hz": 6.040268456375839,
          "psd": 5.331346420975508
        },
        {
          "freq_hz": 6.241610738255033,
          "psd": 3.809379315942233
        },
        {
          "freq_hz": 6.442953020134228,
          "psd": 8.022218926589956
        },
        {
          "freq_hz": 6.644295302013423,
          "psd": 10.977744116254017
        },
        {
          "freq_hz": 6.845637583892617,
          "psd": 9.603180174117613
        },
        {
          "freq_hz": 7.046979865771812,
          "psd": 11.142829695805409
        },
        {
          "freq_hz": 7.248322147651006,
          "psd": 11.168938328931928
        },
        {
          "freq_hz": 7.449664429530201,
          "psd": 13.29865590014426
        },
        {
          "freq_hz": 7.651006711409395,
          "psd": 29.685314758850748
        },
        {
          "freq_hz": 7.85234899328859,
          "psd": 33.700951985280675
        },
        {
          "freq_hz": 8.053691275167784,
          "psd": 22.6120371938857
        },
        {
          "freq_hz": 8.25503355704698,
          "psd": 9.997831073133138
        },
        {
          "freq_hz": 8.456375838926174,
          "psd": 4.044395239109102
        },
        {
          "freq_hz": 8.657718120805368,
          "psd": 3.9382632874177426
        },
        {
          "freq_hz": 8.859060402684563,
          "psd": 3.9584369895111133
        },
        {
          "freq_hz": 9.060402684563758,
          "psd": 2.343697976244578
        },
        {
          "freq_hz": 9.261744966442953,
          "psd": 1.6369640093921873
        },
        {
          "freq_hz": 9.463087248322147,
          "psd": 2.2131682001135333
        },
        {
          "freq_hz": 9.664429530201343,
          "psd": 2.4385603013032204
        },
        {
          "freq_hz": 9.865771812080537,
          "psd": 1.3936960009895087
        },
        {
          "freq_hz": 10.06711409395973,
          "psd": 0.7704472279685849
        },
        {
          "freq_hz": 10.268456375838925,
          "psd": 0.7912180960252034
        },
        {
          "freq_hz": 10.46979865771812,
          "psd": 0.3546015406096748
        },
        {
          "freq_hz": 10.671140939597315,
          "psd": 1.0673213062688622
        },
        {
          "freq_hz": 10.872483221476509,
          "psd": 1.621160620563603
        },
        {
          "freq_hz": 11.073825503355703,
          "psd": 1.0738199440451017
        },
        {
          "freq_hz": 11.275167785234899,
          "psd": 1.215519606634086
        },
        {
          "freq_hz": 11.476510067114093,
          "psd": 1.926703755205866
        },
        {
          "freq_hz": 11.677852348993287,
          "psd": 1.7100921090908514
        },
        {
          "freq_hz": 11.879194630872483,
          "psd": 0.5688086985195792
        },
        {
          "freq_hz": 12.080536912751677,
          "psd": 0.3671667634171483
        },
        {
          "freq_hz": 12.281879194630871,
          "psd": 0.446815589465101
        },
        {
          "freq_hz": 12.483221476510066,
          "psd": 0.502354729870796
        },
        {
          "freq_hz": 12.684563758389261,
          "psd": 0.6743954722085207
        },
        {
          "freq_hz": 12.885906040268456,
          "psd": 0.5755552318472466
        },
        {
          "freq_hz": 13.08724832214765,
          "psd": 0.4787919046648557
        },
        {
          "freq_hz": 13.288590604026846,
          "psd": 0.4596529861496185
        },
        {
          "freq_hz": 13.48993288590604,
          "psd": 0.46078869331276734
        },
        {
          "freq_hz": 13.691275167785234,
          "psd": 0.6408533613349864
        },
        {
          "freq_hz": 13.892617449664428,
          "psd": 0.7181207094363453
        },
        {
          "freq_hz": 14.093959731543624,
          "psd": 0.49584574291136124
        },
        {
          "freq_hz": 14.295302013422818,
          "psd": 0.46709871274313297
        },
        {
          "freq_hz": 14.496644295302012,
          "psd": 0.2602826346395128
        },
        {
          "freq_hz": 14.697986577181208,
          "psd": 0.4803594532524786
        },
        {
          "freq_hz": 14.899328859060402,
          "psd": 0.40849865144980707
        }
      ],
      "psd_tremor_filtered": [
        {
          "freq_hz": 0.0,
          "psd": 0.004563097492404815
        },
        {
          "freq_hz": 0.20134228187919462,
          "psd": 0.002250928193743377
        },
        {
          "freq_hz": 0.40268456375838924,
          "psd": 9.789560708668492e-08
        },
        {
          "freq_hz": 0.6040268456375839,
          "psd": 1.1473749561828486e-07
        },
        {
          "freq_hz": 0.8053691275167785,
          "psd": 1.4172593589268727e-07
        },
        {
          "freq_hz": 1.006711409395973,
          "psd": 1.9005513135379858e-07
        },
        {
          "freq_hz": 1.2080536912751678,
          "psd": 2.4823452524984306e-07
        },
        {
          "freq_hz": 1.4093959731543624,
          "psd": 3.484553138965087e-07
        },
        {
          "freq_hz": 1.610738255033557,
          "psd": 7.417835330622784e-07
        },
        {
          "freq_hz": 1.8120805369127515,
          "psd": 1.5388466800381069e-06
        },
        {
          "freq_hz": 2.013422818791946,
          "psd": 1.0093476093118432e-05
        },
        {
          "freq_hz": 2.2147651006711406,
          "psd": 3.669688304498216e-05
        },
        {
          "freq_hz": 2.4161073825503356,
          "psd": 0.0001430057420806301
        },
        {
          "freq_hz": 2.61744966442953,
          "psd": 0.0015459749329277926
        },
        {
          "freq_hz": 2.8187919463087248,
          "psd": 0.007756757484325324
        },
        {
          "freq_hz": 3.0201342281879193,
          "psd": 0.03288900584538682
        },
        {
          "freq_hz": 3.221476510067114,
          "psd": 0.3086406533094787
        },
        {
          "freq_hz": 3.4228187919463084,
          "psd": 1.2710180170865648
        },
        {
          "freq_hz": 3.624161073825503,
          "psd": 6.257693739630811
        },
        {
          "freq_hz": 3.8255033557046976,
          "psd": 18.087559389520813
        },
        {
          "freq_hz": 4.026845637583892,
          "psd": 16.624431099231597
        },
        {
          "freq_hz": 4.228187919463087,
          "psd": 21.339037803236746
        },
        {
          "freq_hz": 4.429530201342281,
          "psd": 45.43107624582736
        },
        {
          "freq_hz": 4.630872483221476,
          "psd": 30.140335119203147
        },
        {
          "freq_hz": 4.832214765100671,
          "psd": 11.085040499674005
        },
        {
          "freq_hz": 5.033557046979865,
          "psd": 15.656416295939426
        },
        {
          "freq_hz": 5.23489932885906,
          "psd": 19.341253962827412
        },
        {
          "freq_hz": 5.4362416107382545,
          "psd": 17.470980136307393
        },
        {
          "freq_hz": 5.6375838926174495,
          "psd": 12.068128403168348
        },
        {
          "freq_hz": 5.838926174496644,
          "psd": 6.662213554456836
        },
        {
          "freq_hz": 6.040268456375839,
          "psd": 5.330027262085971
        },
        {
          "freq_hz": 6.241610738255033,
          "psd": 3.8101191994224908
        },
        {
          "freq_hz": 6.442953020134228,
          "psd": 8.02354225457884
        },
        {
          "freq_hz": 6.644295302013423,
          "psd": 10.975986717991974
        },
        {
          "freq_hz": 6.845637583892617,
          "psd": 9.60430797257278
        },
        {
          "freq_hz": 7.046979865771812,
          "psd": 11.142633587491092
        },
        {
          "freq_hz": 7.248322147651006,
          "psd": 11.169090283433453
        },
        {
          "freq_hz": 7.449664429530201,
          "psd": 13.297727269625799
        },
        {
          "freq_hz": 7.651006711409395,
          "psd": 29.684752039041104
        },
        {
          "freq_hz": 7.85234899328859,
          "psd": 33.697942256972006
        },
        {
          "freq_hz": 8.053691275167784,
          "psd": 22.60262881867536
        },
        {
          "freq_hz": 8.25503355704698,
          "psd": 9.986434707706787
        },
        {
          "freq_hz": 8.456375838926174,
          "psd": 4.024385717628568
        },
        {
          "freq_hz": 8.657718120805368,
          "psd": 3.8856531389715943
        },
        {
          "freq_hz": 8.859060402684563,
          "psd": 3.8398144669127636
        },
        {
          "freq_hz": 9.060402684563758,
          "psd": 2.207740398764493
        },
        {
          "freq_hz": 9.261744966442953,
          "psd": 1.397112609639178
        },
        {
          "freq_hz": 9.463087248322147,
          "psd": 1.6141917036218025
        },
        {
          "freq_hz": 9.664429530201343,
          "psd": 1.3954625011230124
        },
        {
          "freq_hz": 9.865771812080537,
          "psd": 0.5812000302298436
        },
        {
          "freq_hz": 10.06711409395973,
          "psd": 0.17385591595231725
        },
        {
          "freq_hz": 10.268456375838925,
          "psd": 0.07834117074932442
        },
        {
          "freq_hz": 10.46979865771812,
          "psd": 0.018640678581823257
        },
        {
          "freq_hz": 10.671140939597315,
          "psd": 0.008347341172224751
        },
        {
          "freq_hz": 10.872483221476509,
          "psd": 0.008150773864040152
        },
        {
          "freq_hz": 11.073825503355703,
          "psd": 0.001711774609243195
        },
        {
          "freq_hz": 11.275167785234899,
          "psd": 0.00047873117804768904
        },
        {
          "freq_hz": 11.476510067114093,
          "psd": 0.00020994106667693462
        },
        {
          "freq_hz": 11.677852348993287,
          "psd": 6.713531997134762e-05
        },
        {
          "freq_hz": 11.879194630872483,
          "psd": 9.725263896370816e-06
        },
        {
          "freq_hz": 12.080536912751677,
          "psd": 1.3696772232863927e-06
        },
        {
          "freq_hz": 12.281879194630871,
          "psd": 5.42801046236284e-07
        },
        {
          "freq_hz": 12.483221476510066,
          "psd": 1.8611883300544055e-07
        },
        {
          "freq_hz": 12.684563758389261,
          "psd": 1.0019589455120678e-07
        },
        {
          "freq_hz": 12.885906040268456,
          "psd": 5.0576715203530703e-08
        },
        {
          "freq_hz": 13.08724832214765,
          "psd": 4.107110395850431e-08
        },
        {
          "freq_hz": 13.288590604026846,
          "psd": 2.6074957648709973e-08
        },
        {
          "freq_hz": 13.48993288590604,
          "psd": 1.9460785854807832e-08
        },
        {
          "freq_hz": 13.691275167785234,
          "psd": 1.3982955701774841e-08
        },
        {
          "freq_hz": 13.892617449664428,
          "psd": 1.0142825560460339e-08
        },
        {
          "freq_hz": 14.093959731543624,
          "psd": 7.369632577468626e-09
        },
        {
          "freq_hz": 14.295302013422818,
          "psd": 5.389056619349817e-09
        },
        {
          "freq_hz": 14.496644295302012,
          "psd": 4.036545189362725e-09
        },
        {
          "freq_hz": 14.697986577181208,
          "psd": 3.1945950061736854e-09
        },
        {
          "freq_hz": 14.899328859060402,
          "psd": 2.7903963215794583e-09
        }
      ]
    }
  },
  "directional_analysis": {
    "hsv": {
      "bin_edges": [
        0.0,
        10.0,
        20.0,
        30.0,
        40.0,
        50.0,
        60.0,
        70.0,
        80.0,
        90.0,
        100.0,
        110.0,
        120.0,
        130.0,
        140.0,
        150.0,
        160.0,
        170.0,
        180.0,
        190.0,
        200.0,
        210.0,
        220.0,
        230.0,
        240.0,
        250.0,
        260.0,
        270.0,
        280.0,
        290.0,
        300.0,
        310.0,
        320.0,
        330.0,
        340.0,
        350.0,
        360.0
      ],
      "bin_centers": [
        5.0,
        15.0,
        25.0,
        35.0,
        45.0,
        55.0,
        65.0,
        75.0,
        85.0,
        95.0,
        105.0,
        115.0,
        125.0,
        135.0,
        145.0,
        155.0,
        165.0,
        175.0,
        185.0,
        195.0,
        205.0,
        215.0,
        225.0,
        235.0,
        245.0,
        255.0,
        265.0,
        275.0,
        285.0,
        295.0,
        305.0,
        315.0,
        325.0,
        335.0,
        345.0,
        355.0
      ],
      "power_per_bin": [
        808.0190891876557,
        1257.7604379852248,
        2259.897185326924,
        3714.1723386598005,
        2985.986952401765,
        2931.1902584883755,
        4936.651854658581,
        7760.735400538041,
        8655.744440256027,
        8122.15159803577,
        7835.1512218856515,
        2328.035294974293,
        3137.479869147623,
        2389.4819120875627,
        640.241953970864,
        1385.756701298636,
        2704.1909699962994,
        3112.70535468343,
        1815.5838786177,
        1995.9646879690126,
        1241.768877058613,
        2278.964964897025,
        1613.6744834980632,
        3752.584912677311,
        5154.497543114822,
        7588.941085385733,
        9263.00411387545,
        9332.687173858263,
        5029.2650414586415,
        2871.9527616022033,
        4357.394921426225,
        2450.0822945963514,
        836.6120100083558,
        1179.5386000814515,
        982.413016534673,
        1439.9509413288883
      ],
      "worst_angle": 275.0,
      "best_angle": 145.0,
      "anisotropy_ratio": 14.576812900145427,
      "mean_power": 3615.2842817103137,
      "worst_power": 9332.687173858263,
      "best_power": 640.241953970864,
      "tremor_band_hz": [
        4.0,
        10.0
      ],
      "sampling_rate_hz": 30.0,
      "n_samples": 600,
      "duration_sec": 19.966666662017815,
      "acceleration_tremor_rms": 7173.647316325856
    }
  },
  "improvements": {},
  "stereo_3d": {
    "target_depth_m": 0.5,
    "disparity_px": -315.0360978299588
  }
}